pybiosci/__init__.py
pybiosci/diversity_indicies.py
pybiosci/_diversity_indices_helper/__init__.py
pybiosci/_diversity_indices_helper/aindex.py
pybiosci/_diversity_indices_helper/bindex.py
pybiosci-0.0.5.dist-info/LICENSE.txt
pybiosci-0.0.5.dist-info/METADATA
pybiosci-0.0.5.dist-info/WHEEL
pybiosci-0.0.5.dist-info/top_level.txt
pybiosci-0.0.5.dist-info/RECORD
