Metadata-Version: 2.1
Name: pybiosci
Version: 0.0.5
Summary: Python Bioscience package
Home-page: https://github.com/Mushahid2521/BioDiversity_Index
Author: Md. Mushahidul Islam Shamim
Author-email: mushahidshamim@gmail.com
Project-URL: Bug Tracker, https://github.com/Mushahid2521/BioDiversity_Index/issues
Classifier: Programming Language :: Python :: 3
Classifier: License :: OSI Approved :: MIT License
Classifier: Operating System :: OS Independent
Requires-Python: >=3.6
License-File: LICENSE.txt
Requires-Dist: pandas (>=0.23.3)
